LICENSE.txt
MANIFEST.in
README
VERSION
contributors.txt
requirements.txt
setup.cfg
setup.py
virtualenvwrapper/__init__.py
virtualenvwrapper/nekbot_project.py
virtualenvwrapper.nekbot.egg-info/PKG-INFO
virtualenvwrapper.nekbot.egg-info/SOURCES.txt
virtualenvwrapper.nekbot.egg-info/dependency_links.txt
virtualenvwrapper.nekbot.egg-info/entry_points.txt
virtualenvwrapper.nekbot.egg-info/not-zip-safe
virtualenvwrapper.nekbot.egg-info/requires.txt
virtualenvwrapper.nekbot.egg-info/top_level.txt