Metadata-Version: 1.1
Name: virtualenvwrapper.nekbot
Version: 0.1.0.0
Summary: Virtualenvwrapper installer for NekBot project, a multiprotocol bot.
Home-page: https://nekmo.com
Author: Nekmo
Author-email: contacto@nekmo.com
License: UNKNOWN
Platform: linux
Classifier: Development Status :: 1 - Planning
Classifier: License :: OSI Approved :: MIT License
Classifier: Intended Audience :: Developers
Classifier: Environment :: Console
Classifier: Topic :: Communications :: Chat
Classifier: Topic :: Communications :: Chat :: Internet Relay Chat
Classifier: Topic :: Communications :: Conferencing
Classifier: Operating System :: POSIX :: Linux
Classifier: Programming Language :: Python
Classifier: Programming Language :: Python :: 2
Classifier: Programming Language :: Python :: 2.6
Classifier: Programming Language :: Python :: 2.7
Classifier: Programming Language :: Python :: 3
Classifier: Programming Language :: Python :: 3.2
Classifier: Programming Language :: Python :: 3.3
Classifier: Programming Language :: Python :: 3.4
Provides: virtualenvwrapper.nekbot
